separate/__init__.py
separate/functions/SEPARATE_FUNCTIONS.py
separate/functions/SEPARATE_utilities.py
separate-1.1.0.dist-info/licenses/LICENSE
separate-1.1.0.dist-info/METADATA
separate-1.1.0.dist-info/WHEEL
separate-1.1.0.dist-info/top_level.txt
separate-1.1.0.dist-info/RECORD
