Metadata-Version: 2.4
Name: separate
Version: 1.1.0
Summary: Storm Event Partitioning And Rainfall Analytics for Tipping-bucket rain gage Evaluation (SEPARATE)
Author-email: Brendan Murphy <brendan_murphy@sfu.ca>, Scott David <scott.david@usu.edu>
License-Expression: MIT
Project-URL: GitHub Repository, https://github.com/WatershedsWildfireResearchCollaborative/SEPARATE
Project-URL: Project Website, https://www.burnedwatersheds.com
Project-URL: Issue Tracker, https://github.com/WatershedsWildfireResearchCollaborative/SEPARATE/issues
Requires-Python: <3.13,>=3.11
License-File: LICENSE
Requires-Dist: pandas>=2.1
Requires-Dist: numpy>=1.26
Requires-Dist: matplotlib>=3.8
Requires-Dist: scipy>=1.11
Requires-Dist: openpyxl>=3.1
Dynamic: license-file
